json2schema/__init__.py
json2schema/json2schema.py
json2schema/schema2list.py
json2schema-0.1.1.dist-info/LICENSE
json2schema-0.1.1.dist-info/METADATA
json2schema-0.1.1.dist-info/WHEEL
json2schema-0.1.1.dist-info/top_level.txt
json2schema-0.1.1.dist-info/zip-safe
json2schema-0.1.1.dist-info/RECORD
